xoutil-2.1.11.post1-py3.8-nspkg.pth
tests/__init__.py
tests/customizetestbed.py
tests/test_bases.py
tests/test_bound.py
tests/test_cli.py
tests/test_clisp.py
tests/test_codecs.py
tests/test_collections.py
tests/test_context.py
tests/test_csv.py
tests/test_datetime.py
tests/test_decorators.py
tests/test_dim.py
tests/test_fp.py
tests/test_fs.py
tests/test_functools.py
tests/test_functools2.py
tests/test_graphlib.py
tests/test_infinity.py
tests/test_iterators.py
tests/test_keywords.py
tests/test_modules.py
tests/test_names.py
tests/test_objects.py
tests/test_params.py
tests/test_pprint.py
tests/test_records.py
tests/test_safe.py
tests/test_string.py
tests/test_symbols.py
tests/test_tasking.py
tests/test_textwrap.py
tests/test_tools.py
tests/test_types.py
tests/testbed.py
xotl/tools/__init__.py
xotl/tools/_version.py
xotl/tools/_version.pyi
xotl/tools/bases.py
xotl/tools/bound.py
xotl/tools/clipping.py
xotl/tools/context.py
xotl/tools/context.pyi
xotl/tools/cpystack.py
xotl/tools/crypto.py
xotl/tools/deprecation.py
xotl/tools/infinity.py
xotl/tools/keywords.py
xotl/tools/modules.py
xotl/tools/names.py
xotl/tools/objects.py
xotl/tools/objects.pyi
xotl/tools/params.py
xotl/tools/progress.py
xotl/tools/py.typed
xotl/tools/records.py
xotl/tools/release.py
xotl/tools/string.py
xotl/tools/symbols.py
xotl/tools/tools.py
xotl/tools/versions.py
xotl/tools/web.py
xotl/tools/benchmark/mp.py
xotl/tools/cli/__init__.py
xotl/tools/cli/app.py
xotl/tools/cli/tools.py
xotl/tools/decorator/__init__.py
xotl/tools/decorator/development.py
xotl/tools/decorator/meta.py
xotl/tools/dim/__init__.py
xotl/tools/dim/base.py
xotl/tools/dim/base.pyi
xotl/tools/dim/currencies.py
xotl/tools/dim/meta.py
xotl/tools/fp/__init__.py
xotl/tools/fp/iterators.py
xotl/tools/fp/iterators.pyi
xotl/tools/fp/option.py
xotl/tools/fp/tools.py
xotl/tools/fp/tools.pyi
xotl/tools/fp/prove/__init__.py
xotl/tools/fp/prove/semantic.py
xotl/tools/fs/__init__.py
xotl/tools/fs/path.py
xotl/tools/future/__init__.py
xoutil-2.1.11.post1.dist-info/LICENSE
xoutil-2.1.11.post1.dist-info/METADATA
xoutil-2.1.11.post1.dist-info/WHEEL
xoutil-2.1.11.post1.dist-info/namespace_packages.txt
xoutil-2.1.11.post1.dist-info/top_level.txt
xoutil-2.1.11.post1.dist-info/RECORD
