Metadata-Version: 2.1
Name: xoutil
Version: 2.1.11.post1
Summary: Collection of usefull algorithms and other very disparate stuff
Home-page: https://github.com/merchise/xoutil/
Author: Merchise Autrement
Author-email: project+xoutil@merchise.org
License: GPLv3+
Platform: UNKNOWN
Classifier: Development Status :: 5 - Production/Stable
Classifier: Intended Audience :: Developers
Classifier: License :: OSI Approved :: GNU General Public License v3 or later (GPLv3+)
Classifier: Operating System :: POSIX :: Linux
Classifier: Programming Language :: Python
Classifier: Programming Language :: Python :: 3
Classifier: Topic :: Software Development :: Libraries :: Python Modules
Requires-Python: >=3.5
License-File: LICENSE
Requires-Dist: typing-extensions (~=3.7.4)
Provides-Extra: recommended
Requires-Dist: python-dateutil ; extra == 'recommended'
Requires-Dist: enum34 ; (python_version < "3.4") and extra == 'recommended'
